{"created_at": "Sat Oct 28 13:55:05 +0000 2017", "id": 924273316248080384, "id_str": "924273316248080384", "text": "#Facebook pedir\u00e1 para anunciantes pol\u00edticos comprobar su identidad y ubicaci\u00f3n, esto despu\u00e9s de ayuda rusa a Trump\u2026 https://t.co/ARgNAb6Ick", "display_text_range": [0, 140], "source": "<a href=\"http://www.hootsuite.com\" rel=\"nofollow\">Hootsuite</a>", "truncated": true, "in_reply_to_status_id": null, "in_reply_to_status_id_str": null, "in_reply_to_user_id": null, "in_reply_to_user_id_str": null, "in_reply_to_screen_name": null, "user": {"id": 600275099, "id_str": "600275099", "name": "Capital FM Tepic", "screen_name": "CapitalFMTepic", "location": "Tepic, Nayarit", "url": "http://www.capitalmaxima.mx/", "description": "Estaci\u00f3n de radio juvenil, m\u00fasica en Ingles y Espa\u00f1ol.", "translator_type": "none", "protected": false, "verified": false, "followers_count": 241, "friends_count": 42, "listed_count": 8, "favourites_count": 49, "statuses_count": 15486, "created_at": "Tue Jun 05 17:36:33 +0000 2012", "utc_offset": -18000, "time_zone": "Central Time (US & Canada)", "geo_enabled": false, "lang": "es", "contributors_enabled": false, "is_translator": false, "profile_background_color": "E1E5E9", "profile_background_image_url": "http://pbs.twimg.com/profile_background_images/378800000068280881/60b7a3d0adef68196cf2b6f91aa5bf69.png", "profile_background_image_url_https": "https://pbs.twimg.com/profile_background_images/378800000068280881/60b7a3d0adef68196cf2b6f91aa5bf69.png", "profile_background_tile": false, "profile_link_color": "1B95E0", "profile_sidebar_border_color": "FFFFFF", "profile_sidebar_fill_color": "DDEEF6", "profile_text_color": "333333", "profile_use_background_image": true, "profile_image_url": "http://pbs.twimg.com/profile_images/914954924147957761/KtSrr-Yo_normal.jpg", "profile_image_url_https": "https://pbs.twimg.com/profile_images/914954924147957761/KtSrr-Yo_normal.jpg", "profile_banner_url": "https://pbs.twimg.com/profile_banners/600275099/1506977196", "default_profile": false, "default_profile_image": false, "following": null, "follow_request_sent": null, "notifications": null}, "geo": null, "coordinates": null, "place": null, "contributors": null, "is_quote_status": false, "extended_tweet": {"full_text": "#Facebook pedir\u00e1 para anunciantes pol\u00edticos comprobar su identidad y ubicaci\u00f3n, esto despu\u00e9s de ayuda rusa a Trump https://t.co/vCJceFt3Pi https://t.co/20SVt1NZ75", "display_text_range": [0, 138], "entities": {"hashtags": [{"text": "Facebook", "indices": [0, 9]}], "urls": [{"url": "https://t.co/vCJceFt3Pi", "expanded_url": "http://ow.ly/WZHt30gblwQ", "display_url": "ow.ly/WZHt30gblwQ", "indices": [115, 138]}], "user_mentions": [], "symbols": [], "media": [{"id": 924273312896823301, "id_str": "924273312896823301", "indices": [139, 162], "media_url": "http://pbs.twimg.com/media/DNOtrlqWsAUDD34.jpg", "media_url_https": "https://pbs.twimg.com/media/DNOtrlqWsAUDD34.jpg", "url": "https://t.co/20SVt1NZ75", "display_url": "pic.twitter.com/20SVt1NZ75", "expanded_url": "https://twitter.com/CapitalFMTepic/status/924273316248080384/photo/1", "type": "photo", "sizes": {"small": {"w": 680, "h": 383, "resize": "fit"}, "medium": {"w": 1200, "h": 675, "resize": "fit"}, "large": {"w": 1280, "h": 720, "resize": "fit"}, "thumb": {"w": 150, "h": 150, "resize": "crop"}}}]}, "extended_entities": {"media": [{"id": 924273312896823301, "id_str": "924273312896823301", "indices": [139, 162], "media_url": "http://pbs.twimg.com/media/DNOtrlqWsAUDD34.jpg", "media_url_https": "https://pbs.twimg.com/media/DNOtrlqWsAUDD34.jpg", "url": "https://t.co/20SVt1NZ75", "display_url": "pic.twitter.com/20SVt1NZ75", "expanded_url": "https://twitter.com/CapitalFMTepic/status/924273316248080384/photo/1", "type": "photo", "sizes": {"small": {"w": 680, "h": 383, "resize": "fit"}, "medium": {"w": 1200, "h": 675, "resize": "fit"}, "large": {"w": 1280, "h": 720, "resize": "fit"}, "thumb": {"w": 150, "h": 150, "resize": "crop"}}}]}}, "quote_count": 0, "reply_count": 0, "retweet_count": 0, "favorite_count": 0, "entities": {"hashtags": [{"text": "Facebook", "indices": [0, 9]}], "urls": [{"url": "https://t.co/ARgNAb6Ick", "expanded_url": "https://twitter.com/i/web/status/924273316248080384", "display_url": "twitter.com/i/web/status/9\u2026", "indices": [116, 139]}], "user_mentions": [], "symbols": []}, "favorited": false, "retweeted": false, "possibly_sensitive": false, "filter_level": "low", "lang": "es", "timestamp_ms": "1509198905418"}