{"created_at": "Sat Oct 28 13:54:23 +0000 2017", "id": 924273141278478337, "id_str": "924273141278478337", "text": "Lmfao social media is aggy yo \ud83d\ude02\ud83d\ude02 https://t.co/4j7wHIO700", "display_text_range": [0, 32], "source": "<a href=\"http://twitter.com/download/android\" rel=\"nofollow\">Twitter for Android</a>", "truncated": false, "in_reply_to_status_id": null, "in_reply_to_status_id_str": null, "in_reply_to_user_id": null, "in_reply_to_user_id_str": null, "in_reply_to_screen_name": null, "user": {"id": 207270128, "id_str": "207270128", "name": "Ari DaVille\ud83d\udc60\ud83d\udc8b", "screen_name": "regg_bee", "location": "Newark, NJ", "url": null, "description": ".self explanatory ... #mommyonthemove #followme sc : nurseb23", "translator_type": "none", "protected": false, "verified": false, "followers_count": 375, "friends_count": 514, "listed_count": 3, "favourites_count": 2180, "statuses_count": 10429, "created_at": "Sun Oct 24 23:07:46 +0000 2010", "utc_offset": -25200, "time_zone": "Pacific Time (US & Canada)", "geo_enabled": true, "lang": "en", "contributors_enabled": false, "is_translator": false, "profile_background_color": "C0DEED", "profile_background_image_url": "http://pbs.twimg.com/profile_background_images/208526274/madisyn.jpg", "profile_background_image_url_https": "https://pbs.twimg.com/profile_background_images/208526274/madisyn.jpg", "profile_background_tile": false, "profile_link_color": "0084B4", "profile_sidebar_border_color": "C0DEED", "profile_sidebar_fill_color": "DDEEF6", "profile_text_color": "333333", "profile_use_background_image": true, "profile_image_url": "http://pbs.twimg.com/profile_images/919260003093176320/GHCpxk6g_normal.jpg", "profile_image_url_https": "https://pbs.twimg.com/profile_images/919260003093176320/GHCpxk6g_normal.jpg", "profile_banner_url": "https://pbs.twimg.com/profile_banners/207270128/1492580520", "default_profile": false, "default_profile_image": false, "following": null, "follow_request_sent": null, "notifications": null}, "geo": null, "coordinates": null, "place": null, "contributors": null, "quoted_status_id": 919950598673502209, "quoted_status_id_str": "919950598673502209", "quoted_status": {"created_at": "Mon Oct 16 15:38:09 +0000 2017", "id": 919950598673502209, "id_str": "919950598673502209", "text": "Eminem being honored by Obama for his diss against Trump\n (2017 colorized) https://t.co/5y4nLRFeNu", "display_text_range": [0, 74], "source": "<a href=\"http://twitter.com/download/iphone\" rel=\"nofollow\">Twitter for iPhone</a>", "truncated": false, "in_reply_to_status_id": null, "in_reply_to_status_id_str": null, "in_reply_to_user_id": null, "in_reply_to_user_id_str": null, "in_reply_to_screen_name": null, "user": {"id": 3964438033, "id_str": "3964438033", "name": "dead inside", "screen_name": "DeadSensei", "location": null, "url": null, "description": "show me some titties and feed me pancakes | @IdeoIogy", "translator_type": "none", "protected": false, "verified": false, "followers_count": 37337, "friends_count": 17485, "listed_count": 437, "favourites_count": 6, "statuses_count": 177, "created_at": "Wed Oct 21 02:24:31 +0000 2015", "utc_offset": -25200, "time_zone": "Pacific Time (US & Canada)", "geo_enabled": false, "lang": "en", "contributors_enabled": false, "is_translator": false, "profile_background_color": "C0DEED", "profile_background_image_url": "http://abs.twimg.com/images/themes/theme1/bg.png", "profile_background_image_url_https": "https://abs.twimg.com/images/themes/theme1/bg.png", "profile_background_tile": false, "profile_link_color": "1DA1F2", "profile_sidebar_border_color": "C0DEED", "profile_sidebar_fill_color": "DDEEF6", "profile_text_color": "333333", "profile_use_background_image": true, "profile_image_url": "http://pbs.twimg.com/profile_images/918471257980534784/nRV4rpLb_normal.jpg", "profile_image_url_https": "https://pbs.twimg.com/profile_images/918471257980534784/nRV4rpLb_normal.jpg", "profile_banner_url": "https://pbs.twimg.com/profile_banners/3964438033/1507815588", "default_profile": true, "default_profile_image": false, "following": null, "follow_request_sent": null, "notifications": null}, "geo": null, "coordinates": null, "place": null, "contributors": null, "is_quote_status": false, "quote_count": 176, "reply_count": 37, "retweet_count": 2984, "favorite_count": 6604, "entities": {"hashtags": [], "urls": [], "user_mentions": [], "symbols": [], "media": [{"id": 919950594080694272, "id_str": "919950594080694272", "indices": [75, 98], "media_url": "http://pbs.twimg.com/media/DMRSMPMW4AAK8Bw.jpg", "media_url_https": "https://pbs.twimg.com/media/DMRSMPMW4AAK8Bw.jpg", "url": "https://t.co/5y4nLRFeNu", "display_url": "pic.twitter.com/5y4nLRFeNu", "expanded_url": "https://twitter.com/DeadSensei/status/919950598673502209/photo/1", "type": "photo", "sizes": {"medium": {"w": 686, "h": 446, "resize": "fit"}, "large": {"w": 686, "h": 446, "resize": "fit"}, "thumb": {"w": 150, "h": 150, "resize": "crop"}, "small": {"w": 680, "h": 442, "resize": "fit"}}}]}, "extended_entities": {"media": [{"id": 919950594080694272, "id_str": "919950594080694272", "indices": [75, 98], "media_url": "http://pbs.twimg.com/media/DMRSMPMW4AAK8Bw.jpg", "media_url_https": "https://pbs.twimg.com/media/DMRSMPMW4AAK8Bw.jpg", "url": "https://t.co/5y4nLRFeNu", "display_url": "pic.twitter.com/5y4nLRFeNu", "expanded_url": "https://twitter.com/DeadSensei/status/919950598673502209/photo/1", "type": "photo", "sizes": {"medium": {"w": 686, "h": 446, "resize": "fit"}, "large": {"w": 686, "h": 446, "resize": "fit"}, "thumb": {"w": 150, "h": 150, "resize": "crop"}, "small": {"w": 680, "h": 442, "resize": "fit"}}}]}, "favorited": false, "retweeted": false, "possibly_sensitive": false, "filter_level": "low", "lang": "en"}, "is_quote_status": true, "quote_count": 0, "reply_count": 0, "retweet_count": 0, "favorite_count": 0, "entities": {"hashtags": [], "urls": [{"url": "https://t.co/4j7wHIO700", "expanded_url": "https://twitter.com/DeadSensei/status/919950598673502209", "display_url": "twitter.com/DeadSensei/sta\u2026", "indices": [33, 56]}], "user_mentions": [], "symbols": []}, "favorited": false, "retweeted": false, "possibly_sensitive": false, "filter_level": "low", "lang": "en", "timestamp_ms": "1509198863702"}