{"created_at": "Sat Oct 28 14:02:49 +0000 2017", "id": 924275261553512448, "id_str": "924275261553512448", "text": "RT @Shoq: Delude yourself as you will, but as a Jew, when I see and hear the ginned-up hate of these Trump voters? All I see\u2026 ", "source": "<a href=\"http://twitter.com/download/android\" rel=\"nofollow\">Twitter for Android</a>", "truncated": false, "in_reply_to_status_id": null, "in_reply_to_status_id_str": null, "in_reply_to_user_id": null, "in_reply_to_user_id_str": null, "in_reply_to_screen_name": null, "user": {"id": 337999961, "id_str": "337999961", "name": "Fishgrease", "screen_name": "Fishbooom", "location": null, "url": null, "description": "There is an intricate structure of truth that exists before a writer comes along and nails words to it like cheap fiberboard siding.", "translator_type": "none", "protected": false, "verified": false, "followers_count": 2254, "friends_count": 2392, "listed_count": 86, "favourites_count": 223648, "statuses_count": 105968, "created_at": "Mon Jul 18 22:34:21 +0000 2011", "utc_offset": -25200, "time_zone": "Pacific Time (US & Canada)", "geo_enabled": true, "lang": "en", "contributors_enabled": false, "is_translator": false, "profile_background_color": "C0DEED", "profile_background_image_url": "http://abs.twimg.com/images/themes/theme1/bg.png", "profile_background_image_url_https": "https://abs.twimg.com/images/themes/theme1/bg.png", "profile_background_tile": false, "profile_link_color": "1DA1F2", "profile_sidebar_border_color": "C0DEED", "profile_sidebar_fill_color": "DDEEF6", "profile_text_color": "333333", "profile_use_background_image": true, "profile_image_url": "http://pbs.twimg.com/profile_images/445300793386614786/ReZmMinN_normal.jpeg", "profile_image_url_https": "https://pbs.twimg.com/profile_images/445300793386614786/ReZmMinN_normal.jpeg", "profile_banner_url": "https://pbs.twimg.com/profile_banners/337999961/1396978074", "default_profile": true, "default_profile_image": false, "following": null, "follow_request_sent": null, "notifications": null}, "geo": null, "coordinates": null, "place": null, "contributors": null, "retweeted_status": {"created_at": "Sat Oct 28 04:43:29 +0000 2017", "id": 924134499927187456, "id_str": "924134499927187456", "text": "Delude yourself as you will, but as a Jew, when I see and hear the ginned-up hate of these Trump voters? All I see\u2026 https://t.co/Ju9oCK14MJ", "display_text_range": [0, 140], "source": "<a href=\"https://about.twitter.com/products/tweetdeck\" rel=\"nofollow\">TweetDeck</a>", "truncated": true, "in_reply_to_status_id": null, "in_reply_to_status_id_str": null, "in_reply_to_user_id": null, "in_reply_to_user_id_str": null, "in_reply_to_screen_name": null, "user": {"id": 8431652, "id_str": "8431652", "name": "Count Shoqula", "screen_name": "Shoq", "location": "South F-ing Florida", "url": "http://shoqvalue.com", "description": "I try to see and say things that need seeing and saying. \u2022 I believe in the semantic web. I just don't know what that means.", "translator_type": "none", "protected": false, "verified": false, "followers_count": 25377, "friends_count": 971, "listed_count": 2162, "favourites_count": 8041, "statuses_count": 561216, "created_at": "Sat Aug 25 21:43:05 +0000 2007", "utc_offset": -14400, "time_zone": "Eastern Time (US & Canada)", "geo_enabled": false, "lang": "en", "contributors_enabled": false, "is_translator": false, "profile_background_color": "1A1B1F", "profile_background_image_url": "http://pbs.twimg.com/profile_background_images/194574351/wetcat10.jpg", "profile_background_image_url_https": "https://pbs.twimg.com/profile_background_images/194574351/wetcat10.jpg", "profile_background_tile": false, "profile_link_color": "2FC2EF", "profile_sidebar_border_color": "181A1E", "profile_sidebar_fill_color": "252429", "profile_text_color": "666666", "profile_use_background_image": true, "profile_image_url": "http://pbs.twimg.com/profile_images/924047616110972929/FA1igxV4_normal.jpg", "profile_image_url_https": "https://pbs.twimg.com/profile_images/924047616110972929/FA1igxV4_normal.jpg", "profile_banner_url": "https://pbs.twimg.com/profile_banners/8431652/1436234829", "default_profile": false, "default_profile_image": false, "following": null, "follow_request_sent": null, "notifications": null}, "geo": null, "coordinates": null, "place": null, "contributors": null, "is_quote_status": false, "extended_tweet": {"full_text": "Delude yourself as you will, but as a Jew, when I see and hear the ginned-up hate of these Trump voters? All I see and hear are camp guards. https://t.co/qwfgayTX8v", "display_text_range": [0, 140], "entities": {"hashtags": [], "urls": [], "user_mentions": [], "symbols": [], "media": [{"id": 924134176412065793, "id_str": "924134176412065793", "indices": [141, 164], "media_url": "http://pbs.twimg.com/media/DNMvIx3W4AED--k.jpg", "media_url_https": "https://pbs.twimg.com/media/DNMvIx3W4AED--k.jpg", "url": "https://t.co/qwfgayTX8v", "display_url": "pic.twitter.com/qwfgayTX8v", "expanded_url": "https://twitter.com/Shoq/status/924134499927187456/photo/1", "type": "photo", "sizes": {"small": {"w": 613, "h": 462, "resize": "fit"}, "large": {"w": 613, "h": 462, "resize": "fit"}, "thumb": {"w": 150, "h": 150, "resize": "crop"}, "medium": {"w": 613, "h": 462, "resize": "fit"}}}]}, "extended_entities": {"media": [{"id": 924134176412065793, "id_str": "924134176412065793", "indices": [141, 164], "media_url": "http://pbs.twimg.com/media/DNMvIx3W4AED--k.jpg", "media_url_https": "https://pbs.twimg.com/media/DNMvIx3W4AED--k.jpg", "url": "https://t.co/qwfgayTX8v", "display_url": "pic.twitter.com/qwfgayTX8v", "expanded_url": "https://twitter.com/Shoq/status/924134499927187456/photo/1", "type": "photo", "sizes": {"small": {"w": 613, "h": 462, "resize": "fit"}, "large": {"w": 613, "h": 462, "resize": "fit"}, "thumb": {"w": 150, "h": 150, "resize": "crop"}, "medium": {"w": 613, "h": 462, "resize": "fit"}}}]}}, "quote_count": 3, "reply_count": 3, "retweet_count": 17, "favorite_count": 38, "entities": {"hashtags": [], "urls": [{"url": "https://t.co/Ju9oCK14MJ", "expanded_url": "https://twitter.com/i/web/status/924134499927187456", "display_url": "twitter.com/i/web/status/9\u2026", "indices": [116, 139]}], "user_mentions": [], "symbols": []}, "favorited": false, "retweeted": false, "possibly_sensitive": false, "filter_level": "low", "lang": "en"}, "is_quote_status": false, "quote_count": 0, "reply_count": 0, "retweet_count": 0, "favorite_count": 0, "entities": {"hashtags": [], "urls": [], "user_mentions": [{"screen_name": "Shoq", "name": "Count Shoqula", "id": 8431652, "id_str": "8431652", "indices": [3, 8]}], "symbols": []}, "favorited": false, "retweeted": false, "filter_level": "low", "lang": "en", "timestamp_ms": "1509199369215"}