{"created_at": "Sat Oct 28 13:56:14 +0000 2017", "id": 924273604300234753, "id_str": "924273604300234753", "text": "RT @DrDenaGrayson: @CNN We ALL want Trump and Pence to be indicted for their roles in #TrumpRussia\ud83c\uddf7\ud83c\uddfaand they WILL, but others must fall fir\u2026", "source": "<a href=\"http://twitter.com/download/android\" rel=\"nofollow\">Twitter for Android</a>", "truncated": false, "in_reply_to_status_id": null, "in_reply_to_status_id_str": null, "in_reply_to_user_id": null, "in_reply_to_user_id_str": null, "in_reply_to_screen_name": null, "user": {"id": 440720783, "id_str": "440720783", "name": "Wedgewood Gardens", "screen_name": "Wedgewo0dGdns", "location": "Glen Mills, PA", "url": "http://www.wedgewoodgardens.com", "description": "In business since 1966, we are a retail garden center and wholesale grower. We cater our services to the homeowner and to the landscaper!", "translator_type": "none", "protected": false, "verified": false, "followers_count": 67, "friends_count": 2286, "listed_count": 10, "favourites_count": 1090, "statuses_count": 1375, "created_at": "Mon Dec 19 10:16:36 +0000 2011", "utc_offset": null, "time_zone": null, "geo_enabled": false, "lang": "en", "contributors_enabled": false, "is_translator": false, "profile_background_color": "709397", "profile_background_image_url": "http://abs.twimg.com/images/themes/theme6/bg.gif", "profile_background_image_url_https": "https://abs.twimg.com/images/themes/theme6/bg.gif", "profile_background_tile": false, "profile_link_color": "FF3300", "profile_sidebar_border_color": "86A4A6", "profile_sidebar_fill_color": "A0C5C7", "profile_text_color": "333333", "profile_use_background_image": true, "profile_image_url": "http://pbs.twimg.com/profile_images/763023361911894017/a8ctwusa_normal.jpg", "profile_image_url_https": "https://pbs.twimg.com/profile_images/763023361911894017/a8ctwusa_normal.jpg", "profile_banner_url": "https://pbs.twimg.com/profile_banners/440720783/1470753923", "default_profile": false, "default_profile_image": false, "following": null, "follow_request_sent": null, "notifications": null}, "geo": null, "coordinates": null, "place": null, "contributors": null, "retweeted_status": {"created_at": "Sat Oct 28 02:09:49 +0000 2017", "id": 924095830914629632, "id_str": "924095830914629632", "text": "@CNN We ALL want Trump and Pence to be indicted for their roles in #TrumpRussia\ud83c\uddf7\ud83c\uddfaand they WILL, but others must fall first\u203c\ufe0f 5/", "display_text_range": [5, 127], "source": "<a href=\"http://twitter.com/download/iphone\" rel=\"nofollow\">Twitter for iPhone</a>", "truncated": false, "in_reply_to_status_id": 924095274712170496, "in_reply_to_status_id_str": "924095274712170496", "in_reply_to_user_id": 1651522832, "in_reply_to_user_id_str": "1651522832", "in_reply_to_screen_name": "DrDenaGrayson", "user": {"id": 1651522832, "id_str": "1651522832", "name": "Dr. Dena Grayson", "screen_name": "DrDenaGrayson", "location": "Orlando, FL", "url": "https://en.wikipedia.org/wiki/Dena_Grayson", "description": "Spouse of Rep. @AlanGrayson. #Progressive. Former candidate for US #Congress. Medical #Doctor (MD) and #Scientist (PhD). \"Brain dead moron\" per Trump trolls.", "translator_type": "none", "protected": false, "verified": true, "followers_count": 43953, "friends_count": 293, "listed_count": 324, "favourites_count": 73263, "statuses_count": 30924, "created_at": "Tue Aug 06 23:34:40 +0000 2013", "utc_offset": -10800, "time_zone": "Atlantic Time (Canada)", "geo_enabled": false, "lang": "en", "contributors_enabled": false, "is_translator": false, "profile_background_color": "022330", "profile_background_image_url": "http://pbs.twimg.com/profile_background_images/605865995857567745/ljNLkJHv.jpg", "profile_background_image_url_https": "https://pbs.twimg.com/profile_background_images/605865995857567745/ljNLkJHv.jpg", "profile_background_tile": false, "profile_link_color": "0000E5", "profile_sidebar_border_color": "000000", "profile_sidebar_fill_color": "000000", "profile_text_color": "000000", "profile_use_background_image": true, "profile_image_url": "http://pbs.twimg.com/profile_images/805462926937075712/3vDqj2WO_normal.jpg", "profile_image_url_https": "https://pbs.twimg.com/profile_images/805462926937075712/3vDqj2WO_normal.jpg", "profile_banner_url": "https://pbs.twimg.com/profile_banners/1651522832/1495459194", "default_profile": false, "default_profile_image": false, "following": null, "follow_request_sent": null, "notifications": null}, "geo": null, "coordinates": null, "place": null, "contributors": null, "is_quote_status": false, "quote_count": 5, "reply_count": 21, "retweet_count": 131, "favorite_count": 408, "entities": {"hashtags": [{"text": "TrumpRussia", "indices": [67, 79]}], "urls": [], "user_mentions": [{"screen_name": "CNN", "name": "CNN", "id": 759251, "id_str": "759251", "indices": [0, 4]}], "symbols": []}, "favorited": false, "retweeted": false, "filter_level": "low", "lang": "en"}, "is_quote_status": false, "quote_count": 0, "reply_count": 0, "retweet_count": 0, "favorite_count": 0, "entities": {"hashtags": [{"text": "TrumpRussia", "indices": [86, 98]}], "urls": [], "user_mentions": [{"screen_name": "DrDenaGrayson", "name": "Dr. Dena Grayson", "id": 1651522832, "id_str": "1651522832", "indices": [3, 17]}, {"screen_name": "CNN", "name": "CNN", "id": 759251, "id_str": "759251", "indices": [19, 23]}], "symbols": []}, "favorited": false, "retweeted": false, "filter_level": "low", "lang": "en", "timestamp_ms": "1509198974095"}