{"created_at": "Sat Oct 28 13:52:27 +0000 2017", "id": 924272653782933504, "id_str": "924272653782933504", "text": "@veronicainftl Yet once again it\u2019s not Trump getting indicted \ud83d\ude01 https://t.co/slVg9iGXG6", "display_text_range": [15, 63], "source": "<a href=\"http://twitter.com/download/iphone\" rel=\"nofollow\">Twitter for iPhone</a>", "truncated": false, "in_reply_to_status_id": 924272424555876354, "in_reply_to_status_id_str": "924272424555876354", "in_reply_to_user_id": 3306102544, "in_reply_to_user_id_str": "3306102544", "in_reply_to_screen_name": "veronicainftl", "user": {"id": 840838622337220609, "id_str": "840838622337220609", "name": "Lord\ud83d\udc51Farfetch'D\ud83e\udd86", "screen_name": "Lord_FarfetchD", "location": "Kanto Region ", "url": null, "description": "The Wise One from #TeamInstinct \u26a1\ufe0f", "translator_type": "none", "protected": false, "verified": false, "followers_count": 431, "friends_count": 412, "listed_count": 3, "favourites_count": 1305, "statuses_count": 2115, "created_at": "Sun Mar 12 08:15:24 +0000 2017", "utc_offset": null, "time_zone": null, "geo_enabled": true, "lang": "en", "contributors_enabled": false, "is_translator": false, "profile_background_color": "F5F8FA", "profile_background_image_url": "", "profile_background_image_url_https": "", "profile_background_tile": false, "profile_link_color": "1DA1F2", "profile_sidebar_border_color": "C0DEED", "profile_sidebar_fill_color": "DDEEF6", "profile_text_color": "333333", "profile_use_background_image": true, "profile_image_url": "http://pbs.twimg.com/profile_images/909591109906690049/_6VhYpnF_normal.jpg", "profile_image_url_https": "https://pbs.twimg.com/profile_images/909591109906690049/_6VhYpnF_normal.jpg", "profile_banner_url": "https://pbs.twimg.com/profile_banners/840838622337220609/1490844596", "default_profile": true, "default_profile_image": false, "following": null, "follow_request_sent": null, "notifications": null}, "geo": null, "coordinates": null, "place": null, "contributors": null, "is_quote_status": false, "quote_count": 0, "reply_count": 0, "retweet_count": 0, "favorite_count": 0, "entities": {"hashtags": [], "urls": [], "user_mentions": [{"screen_name": "veronicainftl", "name": "Veronica", "id": 3306102544, "id_str": "3306102544", "indices": [0, 14]}], "symbols": [], "media": [{"id": 924272636179357696, "id_str": "924272636179357696", "indices": [64, 87], "media_url": "http://pbs.twimg.com/tweet_video_thumb/DNOtEMsVoAAE6ar.jpg", "media_url_https": "https://pbs.twimg.com/tweet_video_thumb/DNOtEMsVoAAE6ar.jpg", "url": "https://t.co/slVg9iGXG6", "display_url": "pic.twitter.com/slVg9iGXG6", "expanded_url": "https://twitter.com/Lord_FarfetchD/status/924272653782933504/photo/1", "type": "photo", "sizes": {"medium": {"w": 360, "h": 204, "resize": "fit"}, "large": {"w": 360, "h": 204, "resize": "fit"}, "thumb": {"w": 150, "h": 150, "resize": "crop"}, "small": {"w": 360, "h": 204, "resize": "fit"}}}]}, "extended_entities": {"media": [{"id": 924272636179357696, "id_str": "924272636179357696", "indices": [64, 87], "media_url": "http://pbs.twimg.com/tweet_video_thumb/DNOtEMsVoAAE6ar.jpg", "media_url_https": "https://pbs.twimg.com/tweet_video_thumb/DNOtEMsVoAAE6ar.jpg", "url": "https://t.co/slVg9iGXG6", "display_url": "pic.twitter.com/slVg9iGXG6", "expanded_url": "https://twitter.com/Lord_FarfetchD/status/924272653782933504/photo/1", "type": "animated_gif", "sizes": {"medium": {"w": 360, "h": 204, "resize": "fit"}, "large": {"w": 360, "h": 204, "resize": "fit"}, "thumb": {"w": 150, "h": 150, "resize": "crop"}, "small": {"w": 360, "h": 204, "resize": "fit"}}, "video_info": {"aspect_ratio": [30, 17], "variants": [{"bitrate": 0, "content_type": "video/mp4", "url": "https://video.twimg.com/tweet_video/DNOtEMsVoAAE6ar.mp4"}]}}]}, "favorited": false, "retweeted": false, "possibly_sensitive": false, "filter_level": "low", "lang": "en", "timestamp_ms": "1509198747474"}