{"created_at": "Sat Oct 28 14:01:09 +0000 2017", "id": 924274844996395009, "id_str": "924274844996395009", "text": "Week 23: Mueller Bombs Trump's Big Week - POLITICO https://t.co/gvMEdv6R8m", "source": "<a href=\"http://twitter.com/#!/download/ipad\" rel=\"nofollow\">Twitter for iPad</a>", "truncated": false, "in_reply_to_status_id": null, "in_reply_to_status_id_str": null, "in_reply_to_user_id": null, "in_reply_to_user_id_str": null, "in_reply_to_screen_name": null, "user": {"id": 206495003, "id_str": "206495003", "name": "@heidithemusical", "screen_name": "heidithemusical", "location": "Nottingham forest", "url": null, "description": "Proud liberal, singer-songwriter, pop culture/American Studies addict, and now an oil painter.  The way to know life is to love many things. ~Vincent van Gogh", "translator_type": "none", "protected": false, "verified": false, "followers_count": 499, "friends_count": 2344, "listed_count": 13, "favourites_count": 26092, "statuses_count": 21244, "created_at": "Sat Oct 23 02:31:46 +0000 2010", "utc_offset": -14400, "time_zone": "Eastern Time (US & Canada)", "geo_enabled": false, "lang": "en", "contributors_enabled": false, "is_translator": false, "profile_background_color": "C0DEED", "profile_background_image_url": "http://abs.twimg.com/images/themes/theme1/bg.png", "profile_background_image_url_https": "https://abs.twimg.com/images/themes/theme1/bg.png", "profile_background_tile": false, "profile_link_color": "1DA1F2", "profile_sidebar_border_color": "C0DEED", "profile_sidebar_fill_color": "DDEEF6", "profile_text_color": "333333", "profile_use_background_image": true, "profile_image_url": "http://pbs.twimg.com/profile_images/504364023530278912/-tqRCHrK_normal.jpeg", "profile_image_url_https": "https://pbs.twimg.com/profile_images/504364023530278912/-tqRCHrK_normal.jpeg", "profile_banner_url": "https://pbs.twimg.com/profile_banners/206495003/1407898103", "default_profile": true, "default_profile_image": false, "following": null, "follow_request_sent": null, "notifications": null}, "geo": null, "coordinates": null, "place": null, "contributors": null, "is_quote_status": false, "quote_count": 0, "reply_count": 0, "retweet_count": 0, "favorite_count": 0, "entities": {"hashtags": [], "urls": [{"url": "https://t.co/gvMEdv6R8m", "expanded_url": "https://apple.news/Apcjb6M3nThas5osIXDKd8Q", "display_url": "apple.news/Apcjb6M3nThas5\u2026", "indices": [51, 74]}], "user_mentions": [], "symbols": []}, "favorited": false, "retweeted": false, "possibly_sensitive": false, "filter_level": "low", "lang": "en", "timestamp_ms": "1509199269900"}