{"created_at": "Sat Oct 28 14:02:05 +0000 2017", "id": 924275077645864960, "id_str": "924275077645864960", "text": "@realDonaldTrump  Russia Russia Russia and Trump . I am looking forward to #MuellerTime Guilty of colluding . Look in the mirror Dotard .", "source": "<a href=\"https://about.twitter.com/products/tweetdeck\" rel=\"nofollow\">TweetDeck</a>", "truncated": false, "in_reply_to_status_id": null, "in_reply_to_status_id_str": null, "in_reply_to_user_id": 25073877, "in_reply_to_user_id_str": "25073877", "in_reply_to_screen_name": "realDonaldTrump", "user": {"id": 27952164, "id_str": "27952164", "name": "Shar G", "screen_name": "hapkidogal", "location": null, "url": null, "description": "I am a proud Democrat. I am for rights for all.", "translator_type": "none", "protected": false, "verified": false, "followers_count": 3795, "friends_count": 4537, "listed_count": 174, "favourites_count": 304, "statuses_count": 140143, "created_at": "Tue Mar 31 20:15:54 +0000 2009", "utc_offset": -14400, "time_zone": "Eastern Time (US & Canada)", "geo_enabled": false, "lang": "en", "contributors_enabled": false, "is_translator": false, "profile_background_color": "8B542B", "profile_background_image_url": "http://abs.twimg.com/images/themes/theme8/bg.gif", "profile_background_image_url_https": "https://abs.twimg.com/images/themes/theme8/bg.gif", "profile_background_tile": false, "profile_link_color": "9D582E", "profile_sidebar_border_color": "D9B17E", "profile_sidebar_fill_color": "EADEAA", "profile_text_color": "333333", "profile_use_background_image": true, "profile_image_url": "http://pbs.twimg.com/profile_images/1250729097/Buddah_2.jpg_red_normal.jpg", "profile_image_url_https": "https://pbs.twimg.com/profile_images/1250729097/Buddah_2.jpg_red_normal.jpg", "profile_banner_url": "https://pbs.twimg.com/profile_banners/27952164/1357820900", "default_profile": false, "default_profile_image": false, "following": null, "follow_request_sent": null, "notifications": null}, "geo": null, "coordinates": null, "place": null, "contributors": null, "is_quote_status": false, "quote_count": 0, "reply_count": 0, "retweet_count": 0, "favorite_count": 0, "entities": {"hashtags": [{"text": "MuellerTime", "indices": [75, 87]}], "urls": [], "user_mentions": [{"screen_name": "realDonaldTrump", "name": "Donald J. Trump", "id": 25073877, "id_str": "25073877", "indices": [0, 16]}], "symbols": []}, "favorited": false, "retweeted": false, "filter_level": "low", "lang": "en", "timestamp_ms": "1509199325368"}