{"created_at": "Sat Oct 28 14:02:07 +0000 2017", "id": 924275086093365248, "id_str": "924275086093365248", "text": "Sending this out to all of Trump's 'conquests'. We can only hope his world comes crashing down. https://t.co/Jar7azD8MO", "display_text_range": [0, 95], "source": "<a href=\"http://twitter.com\" rel=\"nofollow\">Twitter Web Client</a>", "truncated": false, "in_reply_to_status_id": null, "in_reply_to_status_id_str": null, "in_reply_to_user_id": null, "in_reply_to_user_id_str": null, "in_reply_to_screen_name": null, "user": {"id": 25730272, "id_str": "25730272", "name": "Brian Mahoney", "screen_name": "_BrianMahoney", "location": "Toronto, Canada. ", "url": "http://gtworld.ca/index.php", "description": "Freelance writer/photographer. Senior fellow at the Broadbean Institute. I tweet about China, technology and politics and now, comedy. brianmahoney.ca", "translator_type": "none", "protected": false, "verified": false, "followers_count": 1085, "friends_count": 637, "listed_count": 18, "favourites_count": 22, "statuses_count": 8060, "created_at": "Sat Mar 21 21:18:42 +0000 2009", "utc_offset": -14400, "time_zone": "Eastern Time (US & Canada)", "geo_enabled": false, "lang": "en", "contributors_enabled": false, "is_translator": false, "profile_background_color": "352726", "profile_background_image_url": "http://pbs.twimg.com/profile_background_images/344247845/DSCF1588.jpg", "profile_background_image_url_https": "https://pbs.twimg.com/profile_background_images/344247845/DSCF1588.jpg", "profile_background_tile": true, "profile_link_color": "1B95E0", "profile_sidebar_border_color": "829D5E", "profile_sidebar_fill_color": "99CC33", "profile_text_color": "3E4415", "profile_use_background_image": true, "profile_image_url": "http://pbs.twimg.com/profile_images/464577053795184640/zR3Gm6fS_normal.jpeg", "profile_image_url_https": "https://pbs.twimg.com/profile_images/464577053795184640/zR3Gm6fS_normal.jpeg", "profile_banner_url": "https://pbs.twimg.com/profile_banners/25730272/1353454892", "default_profile": false, "default_profile_image": false, "following": null, "follow_request_sent": null, "notifications": null}, "geo": null, "coordinates": null, "place": null, "contributors": null, "is_quote_status": false, "quote_count": 0, "reply_count": 0, "retweet_count": 0, "favorite_count": 0, "entities": {"hashtags": [], "urls": [], "user_mentions": [], "symbols": [], "media": [{"id": 924274901124505603, "id_str": "924274901124505603", "indices": [96, 119], "media_url": "http://pbs.twimg.com/media/DNOvICRV4AMPrYM.jpg", "media_url_https": "https://pbs.twimg.com/media/DNOvICRV4AMPrYM.jpg", "url": "https://t.co/Jar7azD8MO", "display_url": "pic.twitter.com/Jar7azD8MO", "expanded_url": "https://twitter.com/_BrianMahoney/status/924275086093365248/photo/1", "type": "photo", "sizes": {"thumb": {"w": 150, "h": 150, "resize": "crop"}, "large": {"w": 647, "h": 434, "resize": "fit"}, "small": {"w": 647, "h": 434, "resize": "fit"}, "medium": {"w": 647, "h": 434, "resize": "fit"}}}]}, "extended_entities": {"media": [{"id": 924274901124505603, "id_str": "924274901124505603", "indices": [96, 119], "media_url": "http://pbs.twimg.com/media/DNOvICRV4AMPrYM.jpg", "media_url_https": "https://pbs.twimg.com/media/DNOvICRV4AMPrYM.jpg", "url": "https://t.co/Jar7azD8MO", "display_url": "pic.twitter.com/Jar7azD8MO", "expanded_url": "https://twitter.com/_BrianMahoney/status/924275086093365248/photo/1", "type": "photo", "sizes": {"thumb": {"w": 150, "h": 150, "resize": "crop"}, "large": {"w": 647, "h": 434, "resize": "fit"}, "small": {"w": 647, "h": 434, "resize": "fit"}, "medium": {"w": 647, "h": 434, "resize": "fit"}}}]}, "favorited": false, "retweeted": false, "possibly_sensitive": false, "filter_level": "low", "lang": "en", "timestamp_ms": "1509199327382"}