{"created_at": "Sat Oct 28 13:59:05 +0000 2017", "id": 924274322583175168, "id_str": "924274322583175168", "text": "The Little-Known Pragmatist Who Is Shaping the Trump Tax Cuts https://t.co/UQA7c6sVc0 https://t.co/h9rhrjSHhL", "display_text_range": [0, 85], "source": "<a href=\"https://dlvrit.com/\" rel=\"nofollow\">dlvr.it</a>", "truncated": false, "in_reply_to_status_id": null, "in_reply_to_status_id_str": null, "in_reply_to_user_id": null, "in_reply_to_user_id_str": null, "in_reply_to_screen_name": null, "user": {"id": 862524188791234560, "id_str": "862524188791234560", "name": "Pioneer Camp Group", "screen_name": "PioneerCampGrp", "location": "Worldwide", "url": "http://www.pioneercamp.group", "description": "Fashion retailer and investor", "translator_type": "none", "protected": false, "verified": false, "followers_count": 21, "friends_count": 100, "listed_count": 1, "favourites_count": 5, "statuses_count": 2074, "created_at": "Thu May 11 04:26:06 +0000 2017", "utc_offset": null, "time_zone": null, "geo_enabled": false, "lang": "en", "contributors_enabled": false, "is_translator": false, "profile_background_color": "F5F8FA", "profile_background_image_url": "", "profile_background_image_url_https": "", "profile_background_tile": false, "profile_link_color": "1DA1F2", "profile_sidebar_border_color": "C0DEED", "profile_sidebar_fill_color": "DDEEF6", "profile_text_color": "333333", "profile_use_background_image": true, "profile_image_url": "http://pbs.twimg.com/profile_images/862527747230281728/wvargVtY_normal.jpg", "profile_image_url_https": "https://pbs.twimg.com/profile_images/862527747230281728/wvargVtY_normal.jpg", "profile_banner_url": "https://pbs.twimg.com/profile_banners/862524188791234560/1494477654", "default_profile": true, "default_profile_image": false, "following": null, "follow_request_sent": null, "notifications": null}, "geo": null, "coordinates": null, "place": null, "contributors": null, "is_quote_status": false, "quote_count": 0, "reply_count": 0, "retweet_count": 0, "favorite_count": 0, "entities": {"hashtags": [], "urls": [{"url": "https://t.co/UQA7c6sVc0", "expanded_url": "http://dlvr.it/Py2Zbw", "display_url": "dlvr.it/Py2Zbw", "indices": [62, 85]}], "user_mentions": [], "symbols": [], "media": [{"id": 924274319886188544, "id_str": "924274319886188544", "indices": [86, 109], "media_url": "http://pbs.twimg.com/media/DNOumM_VAAAq7E0.jpg", "media_url_https": "https://pbs.twimg.com/media/DNOumM_VAAAq7E0.jpg", "url": "https://t.co/h9rhrjSHhL", "display_url": "pic.twitter.com/h9rhrjSHhL", "expanded_url": "https://twitter.com/PioneerCampGrp/status/924274322583175168/photo/1", "type": "photo", "sizes": {"thumb": {"w": 150, "h": 150, "resize": "crop"}, "large": {"w": 1050, "h": 549, "resize": "fit"}, "small": {"w": 680, "h": 356, "resize": "fit"}, "medium": {"w": 1050, "h": 549, "resize": "fit"}}}]}, "extended_entities": {"media": [{"id": 924274319886188544, "id_str": "924274319886188544", "indices": [86, 109], "media_url": "http://pbs.twimg.com/media/DNOumM_VAAAq7E0.jpg", "media_url_https": "https://pbs.twimg.com/media/DNOumM_VAAAq7E0.jpg", "url": "https://t.co/h9rhrjSHhL", "display_url": "pic.twitter.com/h9rhrjSHhL", "expanded_url": "https://twitter.com/PioneerCampGrp/status/924274322583175168/photo/1", "type": "photo", "sizes": {"thumb": {"w": 150, "h": 150, "resize": "crop"}, "large": {"w": 1050, "h": 549, "resize": "fit"}, "small": {"w": 680, "h": 356, "resize": "fit"}, "medium": {"w": 1050, "h": 549, "resize": "fit"}}}]}, "favorited": false, "retweeted": false, "possibly_sensitive": false, "filter_level": "low", "lang": "en", "timestamp_ms": "1509199145347"}