{"id": "709941293477195776", "handle": "realDonaldTrump", "text": "Thank you Marco, I agree! https://t.co/PTfFzFno9p", "is_retweet": "False", "original_author": "", "time": "2016-03-16T03:16:09", "in_reply_to_screen_name": "", "in_reply_to_status_id": "", "in_reply_to_user_id": "", "is_quote_status": "False", "lang": "en", "retweet_count": "15581", "favorite_count": "31896", "longitude": "", "latitude": "", "place_id": "", "place_full_name": "", "place_name": "", "place_type": "", "place_country_code": "", "place_country": "", "place_contained_within": "", "place_attributes": "", "place_bounding_box": "", "source_url": "http://twitter.com/download/iphone", "truncated": "False", "entities": "{'media': [{'display_url': 'pic.twitter.com/PTfFzFno9p', 'expanded_url': 'http://twitter.com/realDonaldTrump/status/709941293477195776/video/1', 'sizes': {'thumb': {'h': 150, 'resize': 'crop', 'w': 150}, 'medium': {'h': 338, 'resize': 'fit', 'w': 600}, 'large': {'h': 576, 'resize': 'fit', 'w': 1024}, 'small': {'h': 191, 'resize': 'fit', 'w': 340}}, 'id_str': '709941212061405184', 'indices': [26, 49], 'id': 709941212061405184, 'url': 'https://t.co/PTfFzFno9p', 'media_url_https': 'https://pbs.twimg.com/ext_tw_video_thumb/709941212061405184/pu/img/0EWxS8Cf2CSEynig.jpg', 'type': 'photo', 'media_url': 'http://pbs.twimg.com/ext_tw_video_thumb/709941212061405184/pu/img/0EWxS8Cf2CSEynig.jpg'}], 'user_mentions': [], 'symbols': [], 'urls': [], 'hashtags': []}", "extended_entities": "{'media': [{'display_url': 'pic.twitter.com/PTfFzFno9p', 'sizes': {'thumb': {'h': 150, 'resize': 'crop', 'w': 150}, 'medium': {'h': 338, 'resize': 'fit', 'w': 600}, 'large': {'h': 576, 'resize': 'fit', 'w': 1024}, 'small': {'h': 191, 'resize': 'fit', 'w': 340}}, 'expanded_url': 'http://twitter.com/realDonaldTrump/status/709941293477195776/video/1', 'indices': [26, 49], 'id': 709941212061405184, 'url': 'https://t.co/PTfFzFno9p', 'video_info': {'variants': [{'content_type': 'application/dash+xml', 'url': 'https://video.twimg.com/ext_tw_video/709941212061405184/pu/pl/VjYFHwU9XdlOxE8Y.mpd'}, {'bitrate': 832000, 'content_type': 'video/mp4', 'url': 'https://video.twimg.com/ext_tw_video/709941212061405184/pu/vid/640x360/A8TFY0iPrQ8nYCpA.mp4'}, {'bitrate': 320000, 'content_type': 'video/mp4', 'url': 'https://video.twimg.com/ext_tw_video/709941212061405184/pu/vid/320x180/eR5VoSrjL_Vq4avB.mp4'}, {'bitrate': 2176000, 'content_type': 'video/mp4', 'url': 'https://video.twimg.com/ext_tw_video/709941212061405184/pu/vid/1280x720/NRyEx0acph-EDs-U.mp4'}, {'content_type': 'application/x-mpegURL', 'url': 'https://video.twimg.com/ext_tw_video/709941212061405184/pu/pl/VjYFHwU9XdlOxE8Y.m3u8'}], 'aspect_ratio': [16, 9], 'duration_millis': 11011}, 'id_str': '709941212061405184', 'additional_media_info': {'monetizable': False}, 'media_url_https': 'https://pbs.twimg.com/ext_tw_video_thumb/709941212061405184/pu/img/0EWxS8Cf2CSEynig.jpg', 'type': 'video', 'media_url': 'http://pbs.twimg.com/ext_tw_video_thumb/709941212061405184/pu/img/0EWxS8Cf2CSEynig.jpg'}]}"}