{"id": "751405672877744128", "handle": "realDonaldTrump", "text": "Last night's horrific execution-style shootings of 12 Dallas law enforcement officers...https://t.co/mwzYU98yTt", "is_retweet": "False", "original_author": "", "time": "2016-07-08T13:20:47", "in_reply_to_screen_name": "", "in_reply_to_status_id": "", "in_reply_to_user_id": "", "is_quote_status": "False", "lang": "en", "retweet_count": "7303", "favorite_count": "19542", "longitude": "", "latitude": "", "place_id": "", "place_full_name": "", "place_name": "", "place_type": "", "place_country_code": "", "place_country": "", "place_contained_within": "", "place_attributes": "", "place_bounding_box": "", "source_url": "http://twitter.com/download/iphone", "truncated": "False", "entities": "{'user_mentions': [], 'symbols': [], 'urls': [{'display_url': 'facebook.com/DonaldTrump/po\u2026', 'expanded_url': 'https://www.facebook.com/DonaldTrump/posts/10157277205810725', 'indices': [88, 111], 'url': 'https://t.co/mwzYU98yTt'}], 'hashtags': []}", "extended_entities": ""}