{"id": "768894337518370818", "handle": "HillaryClinton", "text": "A fringe element has effectively taken over Trump\u2019s campaign and the Republican Party. https://t.co/vJNBtpjpde", "is_retweet": "False", "original_author": "", "time": "2016-08-25T19:34:30", "in_reply_to_screen_name": "", "in_reply_to_status_id": "", "in_reply_to_user_id": "", "is_quote_status": "False", "lang": "en", "retweet_count": "1424", "favorite_count": "2576", "longitude": "", "latitude": "", "place_id": "", "place_full_name": "", "place_name": "", "place_type": "", "place_country_code": "", "place_country": "", "place_contained_within": "", "place_attributes": "", "place_bounding_box": "", "source_url": "https://about.twitter.com/products/tweetdeck", "truncated": "False", "entities": "{'user_mentions': [], 'symbols': [], 'urls': [{'display_url': 'hrc.io/2cbBZWC', 'expanded_url': 'http://hrc.io/2cbBZWC', 'indices': [87, 110], 'url': 'https://t.co/vJNBtpjpde'}], 'hashtags': []}", "extended_entities": ""}