{"id": "756277818993025025", "handle": "HillaryClinton", "text": "\"I already have a concentration camp...it's called Tent City.\" \u2014Joe Arpaio, Trump endorser and #RNCinCLE speaker https://t.co/KH0K2q50em", "is_retweet": "False", "original_author": "", "time": "2016-07-22T00:00:57", "in_reply_to_screen_name": "", "in_reply_to_status_id": "", "in_reply_to_user_id": "", "is_quote_status": "False", "lang": "en", "retweet_count": "1572", "favorite_count": "2239", "longitude": "", "latitude": "", "place_id": "", "place_full_name": "", "place_name": "", "place_type": "", "place_country_code": "", "place_country": "", "place_contained_within": "", "place_attributes": "", "place_bounding_box": "", "source_url": "https://about.twitter.com/products/tweetdeck", "truncated": "False", "entities": "{'user_mentions': [], 'symbols': [], 'urls': [{'display_url': 'hrc.io/2aggEXS', 'expanded_url': 'http://hrc.io/2aggEXS', 'indices': [113, 136], 'url': 'https://t.co/KH0K2q50em'}], 'hashtags': [{'text': 'RNCinCLE', 'indices': [95, 104]}]}", "extended_entities": ""}