{"id": "758456057274347520", "handle": "HillaryClinton", "text": "\u201cWe say their names, but that is not enough\u201d \u2014@ImAngelaBassett on the victims of gun violence https://t.co/5baWnDLqbj", "is_retweet": "False", "original_author": "", "time": "2016-07-28T00:16:30", "in_reply_to_screen_name": "", "in_reply_to_status_id": "", "in_reply_to_user_id": "", "is_quote_status": "False", "lang": "en", "retweet_count": "1111", "favorite_count": "2934", "longitude": "", "latitude": "", "place_id": "", "place_full_name": "", "place_name": "", "place_type": "", "place_country_code": "", "place_country": "", "place_contained_within": "", "place_attributes": "", "place_bounding_box": "", "source_url": "https://about.twitter.com/products/tweetdeck", "truncated": "False", "entities": "{'user_mentions': [{'id_str': '1128218821', 'name': 'Angela Bassett', 'id': 1128218821, 'screen_name': 'ImAngelaBassett', 'indices': [46, 62]}], 'symbols': [], 'urls': [{'display_url': 'snappytv.com/tc/2461067', 'expanded_url': 'http://www.snappytv.com/tc/2461067', 'indices': [94, 117], 'url': 'https://t.co/5baWnDLqbj'}], 'hashtags': []}", "extended_entities": ""}